gtfr/__init__.py
gtfr/provider.py
gtfr-0.0.1.dist-info/LICENSE
gtfr-0.0.1.dist-info/METADATA
gtfr-0.0.1.dist-info/WHEEL
gtfr-0.0.1.dist-info/entry_points.txt
gtfr-0.0.1.dist-info/top_level.txt
gtfr-0.0.1.dist-info/RECORD
