Metadata-Version: 2.1
Name: gtfr
Version: 0.0.1
Summary: A small example package
Home-page: https://github.com/GreyTechno/gtf
Download-URL: https://github.com/GreyTechno/gtf/archive/pypi.zip
Author: MR_GT
Author-email: friendyt89@gmail.com
License: GPL
Keywords: a1,a2,a3,a3,a4,a5,a6,a7,a8,a9
Classifier: Development Status :: 4 - Beta
Classifier: Intended Audience :: Developers
Classifier: Topic :: Software Development :: Libraries :: Python Modules
Classifier: License :: OSI Approved :: GNU General Public License v3 (GPLv3)
Classifier: Programming Language :: Python :: 3
Classifier: Operating System :: OS Independent
Classifier: Environment :: Console
Requires-Python: >=3.5
License-File: LICENSE
Requires-Dist: requests
Requires-Dist: setuptools
